<annotation><filename>37.jpg</filename><folder>users/jending12//tram</folder><source><submittedBy>Jennifer Ding</submittedBy></source><imagesize><nrows>183</nrows><ncols>275</ncols></imagesize><object><name>cable car</name><deleted>0</deleted><verified>0</verified><occluded>no</occluded><attributes></attributes><parts><hasparts></hasparts><ispartof></ispartof></parts><date>17-Apr-2018 22:29:43</date><id>0</id><polygon><username>anonymous</username><pt><x>44</x><y>1</y></pt><pt><x>147</x><y>37</y></pt><pt><x>159</x><y>127</y></pt><pt><x>3</x><y>175</y></pt><pt><x>3</x><y>1</y></pt></polygon></object></annotation>